lolcomicgrabber/LOLComicGrabber.py
lolcomicgrabber/__init__.py
lolcomicgrabber/__main__.py
lolcomicgrabber-0.0.5.dist-info/entry_points.txt
lolcomicgrabber-0.0.5.dist-info/LICENSE
lolcomicgrabber-0.0.5.dist-info/WHEEL
lolcomicgrabber-0.0.5.dist-info/METADATA
lolcomicgrabber-0.0.5.dist-info/RECORD
