Metadata-Version: 2.1
Name: lolcomicgrabber
Version: 0.0.5
Summary: 
License: MIT
Author: Shahriyar Shawon
Author-email: ShahriyarShawon321@gmail.com
Requires-Python: >=3.10,<4.0
Classifier: License :: OSI Approved :: MIT License
Classifier: Programming Language :: Python :: 3
Classifier: Programming Language :: Python :: 3.10
Requires-Dist: beautifulsoup4 (>=4.11.1,<5.0.0)
Requires-Dist: lxml (>=4.8.0,<5.0.0)
Requires-Dist: requests (>=2.27.1,<3.0.0)
